{
  "metadata": {
    "dico": "0506",
    "name": "Oleiros",
    "last_updated": "2025-10-25T21:32:36Z",
    "api_version": "1.0.0"
  },
  "dimensions": {
    "coesao_territorial": {
      "sub_dimensions": {
        "dinamicas_sociais": {
          "gavetas": {
            "desigualdade": {
              "indicators": {
                "beneficiarios_rsi": {
                  "normalized": 97.8,
                  "raw": 7.63,
                  "unit": "%"
                },
                "disparidade_ganho": {
                  "normalized": 72.7,
                  "raw": 10.6,
                  "unit": "%"
                },
                "indice_gini": {
                  "normalized": 74.74,
                  "raw": 39.8,
                  "unit": "n"
                },
                "ganho_medio_mensal": {
                  "normalized": 15.4,
                  "raw": 1187.9,
                  "unit": "€"
                },
                "per_pop_ensino_sec_cpmpleto": {
                  "normalized": 8.45,
                  "raw": 25.18,
                  "unit": "%"
                },
                "txt_desemprego": {
                  "normalized": 96.82,
                  "raw": 3.23,
                  "unit": "%"
                },
                "pop_risco_pobreza": {
                  "normalized": 55.55,
                  "raw": 24.46,
                  "unit": "%"
                }
              }
            },
            "isolamento": {
              "indicators": {
                "agregados_unipessoais": {
                  "normalized": 20.87,
                  "raw": 34.76,
                  "unit": "%"
                },
                "residentes_65_ou_mais_anos": {
                  "normalized": 5.1,
                  "raw": 45.64,
                  "unit": "%"
                },
                "txt_bruta_natalidade": {
                  "normalized": 32.29,
                  "raw": 5.3,
                  "unit": "%"
                },
                "txt_bruta_crescimento_efectivo": {
                  "normalized": 54.51,
                  "raw": 0.53,
                  "unit": "%"
                }
              }
            }
          }
        },
        "dinamicas_habitacao": {
          "gavetas": {
            "acesso_mercado": {
              "indicators": {
                "a_apoarrend": {
                  "normalized": 99.99,
                  "raw": 1,
                  "unit": "%"
                },
                "proporcao_al": {
                  "normalized": 98.76,
                  "raw": 1.19,
                  "unit": "%"
                },
                "txt_esforco_2023": {
                  "normalized": 81.84,
                  "raw": 25.96,
                  "unit": "%"
                },
                "variacao_txt_esforco_2017_2023": {
                  "normalized": 62.37,
                  "raw": -0.41,
                  "unit": "%"
                },
                "prop_fogos_hab_social": {
                  "normalized": 100,
                  "raw": 0,
                  "unit": "%"
                }
              }
            },
            "conservacao_parque": {
              "indicators": {
                "prop_vagos": {
                  "normalized": 84.08,
                  "raw": 9,
                  "unit": "%"
                },
                "prop_edificado_reparacoes_prof_med": {
                  "normalized": 70.06,
                  "raw": 13.53,
                  "unit": "%"
                },
                "ind_env_edif": {
                  "normalized": 88.85,
                  "raw": 1361.8,
                  "unit": "n"
                },
                "aru_oru": {
                  "normalized": 0,
                  "raw": 0,
                  "unit": "n"
                },
                "prop_drenagem_agua": {
                  "normalized": 5.79,
                  "raw": 59,
                  "unit": "%"
                },
                "prop_abast_agua": {
                  "normalized": 100,
                  "raw": 100,
                  "unit": "%"
                },
                "r_edi_habfa": {
                  "normalized": 77.8,
                  "raw": 22.2,
                  "unit": null
                }
              }
            }
          }
        }
      }
    },
    "sustentabilidade_ambiental": {
      "sub_dimensions": {
        "eficiencia_energetica": {
          "gavetas": {
            "habitacao": {
              "indicators": {
                "consumo_energetico": {
                  "normalized": 84.43,
                  "raw": 1322.1,
                  "unit": "kWh/hab."
                },
                "alojamentos_ar_condicionado": {
                  "normalized": 0.35,
                  "raw": 187,
                  "unit": "n"
                },
                "prop_sem_aquecimento": {
                  "normalized": 99.08,
                  "raw": 4.29,
                  "unit": "n"
                },
                "certificacao_a_c": {
                  "normalized": 53.62,
                  "raw": 37,
                  "unit": null
                }
              }
            },
            "transportes": {
              "indicators": {
                "prop_pedonal": {
                  "normalized": 22.64,
                  "raw": 19.3,
                  "unit": "%"
                },
                "prop_transporte_colectivo": {
                  "normalized": 23.81,
                  "raw": 8.8,
                  "unit": "%"
                },
                "emicao_co2_transportes": {
                  "normalized": 99.56,
                  "raw": 4.44,
                  "unit": null
                }
              }
            }
          }
        },
        "catastrofes_naturais": {
          "indicators": {
            "cheias_inu": {
              "normalized": 100,
              "raw": 0,
              "unit": null
            },
            "incendios": {
              "normalized": 6.39,
              "raw": 87.09,
              "unit": null
            },
            "inund_galg": {
              "normalized": 100,
              "raw": 0,
              "unit": null
            },
            "movi_massa": {
              "normalized": 63.6,
              "raw": 20.04,
              "unit": null
            },
            "nevoes_pon": {
              "normalized": 58.87,
              "raw": 34.61,
              "unit": null
            },
            "onda_de_calor": {
              "normalized": 33.33,
              "raw": 75,
              "unit": null
            },
            "onda_de_fr": {
              "normalized": 44.38,
              "raw": 66.67,
              "unit": null
            },
            "seca_ponde": {
              "normalized": 50,
              "raw": 66.67,
              "unit": null
            },
            "sismo_pord": {
              "normalized": 93.09,
              "raw": 33.64,
              "unit": null
            },
            "tsunami_po": {
              "normalized": 100,
              "raw": 0,
              "unit": null
            },
            "ventos_for": {
              "normalized": 1.73,
              "raw": 98.74,
              "unit": null
            }
          }
        }
      }
    }
  }
}
