{
  "metadata": {
    "dico": "0904",
    "name": "Figueira de Castelo Rodrigo",
    "last_updated": "2025-10-25T21:32:36Z",
    "api_version": "1.0.0"
  },
  "dimensions": {
    "coesao_territorial": {
      "sub_dimensions": {
        "dinamicas_sociais": {
          "gavetas": {
            "desigualdade": {
              "indicators": {
                "beneficiarios_rsi": {
                  "normalized": 59.12,
                  "raw": 58.89,
                  "unit": "%"
                },
                "disparidade_ganho": {
                  "normalized": 95.8,
                  "raw": 1.8,
                  "unit": "%"
                },
                "indice_gini": {
                  "normalized": 71.13,
                  "raw": 40.5,
                  "unit": "n"
                },
                "ganho_medio_mensal": {
                  "normalized": 5.46,
                  "raw": 1036.3,
                  "unit": "€"
                },
                "per_pop_ensino_sec_cpmpleto": {
                  "normalized": 10.9,
                  "raw": 26.28,
                  "unit": "%"
                },
                "txt_desemprego": {
                  "normalized": 67.1,
                  "raw": 8.27,
                  "unit": "%"
                },
                "pop_risco_pobreza": {
                  "normalized": 42.8,
                  "raw": 28.11,
                  "unit": "%"
                }
              }
            },
            "isolamento": {
              "indicators": {
                "agregados_unipessoais": {
                  "normalized": 42.2,
                  "raw": 29.14,
                  "unit": "%"
                },
                "residentes_65_ou_mais_anos": {
                  "normalized": 25.81,
                  "raw": 38,
                  "unit": "%"
                },
                "txt_bruta_natalidade": {
                  "normalized": 35.42,
                  "raw": 5.6,
                  "unit": "%"
                },
                "txt_bruta_crescimento_efectivo": {
                  "normalized": 37.33,
                  "raw": -0.46,
                  "unit": "%"
                }
              }
            }
          }
        },
        "dinamicas_habitacao": {
          "gavetas": {
            "acesso_mercado": {
              "indicators": {
                "a_apoarrend": {
                  "normalized": 99.92,
                  "raw": 7,
                  "unit": "%"
                },
                "proporcao_al": {
                  "normalized": 93.15,
                  "raw": 6.55,
                  "unit": "%"
                },
                "txt_esforco_2023": {
                  "normalized": 80.76,
                  "raw": 26.63,
                  "unit": "%"
                },
                "variacao_txt_esforco_2017_2023": {
                  "normalized": 57.58,
                  "raw": 1.5,
                  "unit": "%"
                },
                "prop_fogos_hab_social": {
                  "normalized": 96.79,
                  "raw": 0.34,
                  "unit": "%"
                }
              }
            },
            "conservacao_parque": {
              "indicators": {
                "prop_vagos": {
                  "normalized": 39.3,
                  "raw": 18,
                  "unit": "%"
                },
                "prop_edificado_reparacoes_prof_med": {
                  "normalized": 54.04,
                  "raw": 19,
                  "unit": "%"
                },
                "ind_env_edif": {
                  "normalized": 85.26,
                  "raw": 1773.4,
                  "unit": "n"
                },
                "aru_oru": {
                  "normalized": 0,
                  "raw": 0,
                  "unit": "n"
                },
                "prop_drenagem_agua": {
                  "normalized": 10.19,
                  "raw": 100,
                  "unit": "%"
                },
                "prop_abast_agua": {
                  "normalized": 100,
                  "raw": 100,
                  "unit": "%"
                },
                "r_edi_habfa": {
                  "normalized": 100,
                  "raw": 0,
                  "unit": null
                }
              }
            }
          }
        }
      }
    },
    "sustentabilidade_ambiental": {
      "sub_dimensions": {
        "eficiencia_energetica": {
          "gavetas": {
            "habitacao": {
              "indicators": {
                "consumo_energetico": {
                  "normalized": 82.95,
                  "raw": 1356.2,
                  "unit": "kWh/hab."
                },
                "alojamentos_ar_condicionado": {
                  "normalized": 0.37,
                  "raw": 198,
                  "unit": "n"
                },
                "prop_sem_aquecimento": {
                  "normalized": 95.84,
                  "raw": 7.19,
                  "unit": "n"
                },
                "certificacao_a_c": {
                  "normalized": 26.09,
                  "raw": 18,
                  "unit": null
                }
              }
            },
            "transportes": {
              "indicators": {
                "prop_pedonal": {
                  "normalized": 39.43,
                  "raw": 28.2,
                  "unit": "%"
                },
                "prop_transporte_colectivo": {
                  "normalized": 30.95,
                  "raw": 11.2,
                  "unit": "%"
                },
                "emicao_co2_transportes": {
                  "normalized": 99.52,
                  "raw": 4.86,
                  "unit": null
                }
              }
            }
          }
        },
        "catastrofes_naturais": {
          "indicators": {
            "cheias_inu": {
              "normalized": 100,
              "raw": 0,
              "unit": null
            },
            "incendios": {
              "normalized": 25.09,
              "raw": 70.64,
              "unit": null
            },
            "inund_galg": {
              "normalized": 100,
              "raw": 0,
              "unit": null
            },
            "movi_massa": {
              "normalized": 85.03,
              "raw": 8.24,
              "unit": null
            },
            "nevoes_pon": {
              "normalized": 64.74,
              "raw": 29.67,
              "unit": null
            },
            "onda_de_calor": {
              "normalized": 0,
              "raw": 100,
              "unit": null
            },
            "onda_de_fr": {
              "normalized": 0,
              "raw": 100,
              "unit": null
            },
            "seca_ponde": {
              "normalized": 50,
              "raw": 66.67,
              "unit": null
            },
            "sismo_pord": {
              "normalized": 90.16,
              "raw": 35.74,
              "unit": null
            },
            "tsunami_po": {
              "normalized": 100,
              "raw": 0,
              "unit": null
            },
            "ventos_for": {
              "normalized": 68.27,
              "raw": 50.35,
              "unit": null
            }
          }
        }
      }
    }
  }
}
