{
  "metadata": {
    "dico": "1406",
    "name": "Cartaxo",
    "last_updated": "2025-10-25T21:32:36Z",
    "api_version": "1.0.0"
  },
  "dimensions": {
    "coesao_territorial": {
      "sub_dimensions": {
        "dinamicas_sociais": {
          "gavetas": {
            "desigualdade": {
              "indicators": {
                "beneficiarios_rsi": {
                  "normalized": 93.13,
                  "raw": 13.82,
                  "unit": "%"
                },
                "disparidade_ganho": {
                  "normalized": 80.05,
                  "raw": 7.8,
                  "unit": "%"
                },
                "indice_gini": {
                  "normalized": 69.07,
                  "raw": 40.9,
                  "unit": "n"
                },
                "ganho_medio_mensal": {
                  "normalized": 19.05,
                  "raw": 1243.7,
                  "unit": "€"
                },
                "per_pop_ensino_sec_cpmpleto": {
                  "normalized": 47.88,
                  "raw": 42.91,
                  "unit": "%"
                },
                "txt_desemprego": {
                  "normalized": 70.17,
                  "raw": 7.75,
                  "unit": "%"
                },
                "pop_risco_pobreza": {
                  "normalized": 84.15,
                  "raw": 16.28,
                  "unit": "%"
                }
              }
            },
            "isolamento": {
              "indicators": {
                "agregados_unipessoais": {
                  "normalized": 55.9,
                  "raw": 25.53,
                  "unit": "%"
                },
                "residentes_65_ou_mais_anos": {
                  "normalized": 60.33,
                  "raw": 25.27,
                  "unit": "%"
                },
                "txt_bruta_natalidade": {
                  "normalized": 44.79,
                  "raw": 6.5,
                  "unit": "%"
                },
                "txt_bruta_crescimento_efectivo": {
                  "normalized": 70.14,
                  "raw": 1.43,
                  "unit": "%"
                }
              }
            }
          }
        },
        "dinamicas_habitacao": {
          "gavetas": {
            "acesso_mercado": {
              "indicators": {
                "a_apoarrend": {
                  "normalized": 99.66,
                  "raw": 28,
                  "unit": "%"
                },
                "proporcao_al": {
                  "normalized": 98.07,
                  "raw": 1.85,
                  "unit": "%"
                },
                "txt_esforco_2023": {
                  "normalized": 78.57,
                  "raw": 27.99,
                  "unit": "%"
                },
                "variacao_txt_esforco_2017_2023": {
                  "normalized": 49.52,
                  "raw": 4.73,
                  "unit": "%"
                },
                "prop_fogos_hab_social": {
                  "normalized": 99.71,
                  "raw": 0.03,
                  "unit": "%"
                }
              }
            },
            "conservacao_parque": {
              "indicators": {
                "prop_vagos": {
                  "normalized": 60.2,
                  "raw": 13.8,
                  "unit": "%"
                },
                "prop_edificado_reparacoes_prof_med": {
                  "normalized": 57.82,
                  "raw": 17.71,
                  "unit": "%"
                },
                "ind_env_edif": {
                  "normalized": 90.1,
                  "raw": 1218,
                  "unit": "n"
                },
                "aru_oru": {
                  "normalized": 6.25,
                  "raw": 2,
                  "unit": "n"
                },
                "prop_drenagem_agua": {
                  "normalized": 7.19,
                  "raw": 72,
                  "unit": "%"
                },
                "prop_abast_agua": {
                  "normalized": 93.62,
                  "raw": 97,
                  "unit": "%"
                },
                "r_edi_habfa": {
                  "normalized": 84,
                  "raw": 16,
                  "unit": null
                }
              }
            }
          }
        }
      }
    },
    "sustentabilidade_ambiental": {
      "sub_dimensions": {
        "eficiencia_energetica": {
          "gavetas": {
            "habitacao": {
              "indicators": {
                "consumo_energetico": {
                  "normalized": 77.35,
                  "raw": 1485.2,
                  "unit": "kWh/hab."
                },
                "alojamentos_ar_condicionado": {
                  "normalized": 4.26,
                  "raw": 2170,
                  "unit": "n"
                },
                "prop_sem_aquecimento": {
                  "normalized": 73.91,
                  "raw": 26.82,
                  "unit": "n"
                },
                "certificacao_a_c": {
                  "normalized": 55.07,
                  "raw": 38,
                  "unit": null
                }
              }
            },
            "transportes": {
              "indicators": {
                "prop_pedonal": {
                  "normalized": 14.53,
                  "raw": 15,
                  "unit": "%"
                },
                "prop_transporte_colectivo": {
                  "normalized": 38.1,
                  "raw": 13.6,
                  "unit": "%"
                },
                "emicao_co2_transportes": {
                  "normalized": 94.04,
                  "raw": 56.26,
                  "unit": null
                }
              }
            }
          }
        },
        "catastrofes_naturais": {
          "indicators": {
            "cheias_inu": {
              "normalized": 38.5,
              "raw": 32.95,
              "unit": null
            },
            "incendios": {
              "normalized": 78.27,
              "raw": 23.87,
              "unit": null
            },
            "inund_galg": {
              "normalized": 71.96,
              "raw": 18.91,
              "unit": null
            },
            "movi_massa": {
              "normalized": 99.36,
              "raw": 0.35,
              "unit": null
            },
            "nevoes_pon": {
              "normalized": 100,
              "raw": 0,
              "unit": null
            },
            "onda_de_calor": {
              "normalized": 33.33,
              "raw": 75,
              "unit": null
            },
            "onda_de_fr": {
              "normalized": 88.76,
              "raw": 33.33,
              "unit": null
            },
            "seca_ponde": {
              "normalized": 100,
              "raw": 33.33,
              "unit": null
            },
            "sismo_pord": {
              "normalized": 4.63,
              "raw": 96.7,
              "unit": null
            },
            "tsunami_po": {
              "normalized": 80.7,
              "raw": 13.38,
              "unit": null
            },
            "ventos_for": {
              "normalized": 91.68,
              "raw": 33.33,
              "unit": null
            }
          }
        }
      }
    }
  }
}
